<?xml version="1.0" encoding="UTF-8"?>
<!-- Related XMLSchema file: conf/schemas/scenario.xsd -->
<!-- name="Send 3GPP CX Multimedia Authentication answer (MAR/MAA)" -->
<scenario>

    <label name="ReceiveRequestMAR"/>
    
    <receiveMessageDIAMETER name="Receive Request 3GPP/SH/UDR" timeout="0" request="true" type="User-Data:306">
		<parameter name="hopByHop" operation="protocol.setFromMessage" value="header.hopByHop"/>
		<parameter name="endToEnd" operation="protocol.setFromMessage" value="header.endToEnd"/>
    </receiveMessageDIAMETER>

    <sendMessageDIAMETER name="Send Answer 3GPP/SH/UDR">
	<header request="false" command="User-Data" applicationId="3GPP Sh" proxiable="true" hopByHop="[hopByHop]" endToEnd="[endToEnd]"/>
	<avp code="Origin-Host" value="[remoteHostDIAM]"/>
	<avp code="Origin-Realm" value="[remoteRealmDIAM]"/>
	<avp code="Vendor-Specific-Application-Id">
		<avp code="Vendor-Id" value="TGPP"/>
		<avp code="Auth-Application-Id" value="3GPP Sh"/>
	</avp>
	<avp code="Session-Id" value="CXCSCFCX.sip.pfdev.fr;45e45ee4;046725;5cd579ef"/>
	<avp code="Auth-Session-State" value="NO_STATE_MAINTAINED"/>
	<avp code="Result-Code" value="DIAMETER_SUCCESS"/>		
	<avp code="Supported-Features" vendorId="[vendorID]">
		<avp code="Vendor-Id" value="TGPP"/>
		<avp code="Feature-List-ID" value="1"/>
		<avp code="Feature-List" value="1"/> 
	</avp>
	<avp code="Supported-Features" vendorId="[vendorID]">
		<avp code="Vendor-Id" value="TGPP"/>
		<avp code="Feature-List-ID" value="2"/>
		<avp code="Feature-List" value="2"/> 
	</avp>
	<avp code="Supported-Features" vendorId="[vendorID]">
		<avp code="Vendor-Id" value="TGPP"/>
		<avp code="Feature-List-ID" value="3"/>
		<avp code="Feature-List" value="2"/> 
	</avp>
	<avp code="User-Data" value="User-Data" vendorId="[vendorID]"/>
    </sendMessageDIAMETER>

    <goto name="goto ReceiveRequestMAR" label="ReceiveRequestMAR" />    
    
</scenario>
