<?xml version="1.0" encoding="UTF-8"?>
<!-- Related XMLSchema file: conf/schemas/scenario.xsd -->

<scenario>

  	<parameter name="[domainName]" operation="set" value="devoteam.com"/>
  	<parameter name="[userName]" operation="set" value="alice"/>
  	<parameter name="[clientName]" operation="set" value="alice"/>
	<parameter name="[localTag]" operation="string.random" value="10"/>
	<parameter name="[newCallId]" operation="number.random" value="10000000"/>
	<parameter name="[newCseq]" operation="number.random" value="10000000"/>
  	<parameter name="[newBranchId]" operation="string.random" value="10"/>

	<sendMessageSIP name="Send MESSAGE"  destScenario="bob">
<!--******************* BEGIN MESSAGE ********************-->
<![CDATA[MESSAGE sip:0033660648607@[domainName] SIP/2.0
To: sip:0033660648607@[domainName]
From: "[clientName]"<sip:[clientName]@[domainName]>;tag=[localTag]
Via: SIP/2.0/[transportResponse] [localSIP];branch=z9hG4bK[newBranchId];id=[clientName]
Call-ID: [newCallId]
CSeq: [newCseq] MESSAGE
Contact: <sip:bob@[localSIP]>;+g.poc.talkburst
Max-Forwards: 70
User-Agent: PoC-client/OMA1.0 Siemens/v2.0
Accept-Contact: +g.poc.groupad;require;explicit
Server: PoC-client/OMA1.0 Siemens/v2.0
Route: <sip:[remoteSIP];transport=[transportRequest];lr>
Route: <sip:[localSIP];lr;id=[inviteeName1]>
Expires: 0
Content-Type: text/plain
Content-Length: x

Hello ]]>
<!--******************** END MESSAGE *********************-->
        </sendMessageSIP>

	<receiveMessageSIP name="receive MESSAGE response" request="false" type="MESSAGE">
		<parameter name="[StatusCode]" operation="protocol.setFromMessage" value="firstline.StatusCode"/>	
		<parameter name="[WWWAuthRealm]" operation="protocol.setFromMessage" value="header.WWW-Authenticate.Attribute.realm"/>									
		<parameter name="[WWWAuthNonce]" operation="protocol.setFromMessage" value="header.WWW-Authenticate.Attribute.nonce"/>					
		<parameter name="[WWWAuthQop]" operation="protocol.setFromMessage" value="header.WWW-Authenticate.Attribute.qop"/>
	</receiveMessageSIP>

	<if>
	<condition>
		<test parameter="[StatusCode]" condition="string.equals" value="407" />
	</condition>
	<then>	

		<parameter name="[UserName]" operation="set" value="33975621672@sip.mobistar.com"/>
		<parameter name="[Password]" operation="set" value="imt30imt30"/>
		<parameter name="[HA1]" operation="string.digest" value2="MD5" value="[UserName]:[WWWAuthRealm]:[Password]" />

		<parameter name="[Method]" operation="set" value="MESSAGE"/>
		<parameter name="[URI]"      operation="set" value="sip:sip.mobistar.com:5060" />
		<parameter name="[HA2]" operation="string.digest" value2="MD5" value="[Method]:[URI]" />
		
		<parameter name="[NonceCount]" operation="set" value="00000001" />
		<parameter name="[CNonce]"     operation="set" value="11fc4a0e" />
  		<parameter name="[AuthResponse]" operation="string.digest"  value2="MD5" value="[HA1]:[WWWAuthNonce]:[NonceCount]:[CNonce]:[WWWAuthQop]:[HA2]" />
			
  		<parameter name="[newBranchId]" operation="string.random" value="10"/>
			
		<sendMessageSIP name="Send MESSAGE"  destScenario="bob">
<!--******************* BEGIN MESSAGE ********************-->
<![CDATA[[Method] [URI] SIP/2.0
To: sip:0033660648607@[domainName]
From: "[clientName]"<sip:[clientName]@[domainName]>;tag=[localTag]
Via: SIP/2.0/[transportResponse] [localSIP];branch=z9hG4bK[newBranchId];id=[clientName]
Call-ID: [newCallId]
CSeq: [newCseq] MESSAGE
Contact: <sip:bob@[localSIP]>;+g.poc.talkburst
Max-Forwards: 70
User-Agent: PoC-client/OMA1.0 Siemens/v2.0
Accept-Contact: +g.poc.groupad;require;explicit
Server: PoC-client/OMA1.0 Siemens/v2.0
Route: <sip:[remoteSIP];transport=[transportRequest];lr>
Route: <sip:[localSIP];lr;id=[inviteeName1]>
Authorization: Digest username="[UserName]", realm="[WWWAuthRealm]", nonce="[WWWAuthNonce]", opaque="", response="[AuthResponse]", cnonce="[CNonce]", qop="[WWWAuthQop]", nc=[NonceCount]
Expires: 0
Content-Type: text/plain
Content-Length: x

Hello
]]>
<!--******************** END MESSAGE *********************-->
	        </sendMessageSIP>
	</then>
	</if>
	
	<receiveMessageSIP name="receive MESSAGE response" request="false" type="MESSAGE">
	</receiveMessageSIP>
		
</scenario>
