<?xml version="1.0" encoding="UTF-8" ?> 
<scenario>
	<!-- send IP/UDP/SIP REGISTER message -->
	<createProbeETHERNET name="capture" networkInterface="[Host-Address]" captureFilter="" />
	<parameter name="BinaryIP" operation="binary.fromIp" value="[Host-Address]" />
	
	<sendMessageETHERNET name="send packet" probe="capture"> <!-- nic="0" is eth0 -->
		<ethernet remoteMac="ff:ff:ff:ff:ff:ff" type="0806" /> <!-- type="0806" is for ARP payload -->
		<data format="binary">h0001</data> <!-- Hardware Type 0001 for ETH -->
		<data format="binary">h0800</data> 		<!-- Protocol type 0800 for IP -->
		<data format="binary">h06</data> 	<!-- Hardware Size 06 for ETHERNET (6 bytes) -->
		<data format="binary">h04</data> 	<!-- Protocol Size 04 for IPv4 (4 byte) -->
  		<data format="binary">h0001</data> <!-- OP code 0001 for request-->
		<data format="binary">h0022192313d9</data> <!-- @MAC src -->
		<data format="binary">h[BinaryIP]</data> <!-- @IP src -->
		<data format="binary">h000000000000</data> <!-- @MAC dest (the one we want to find) -->
		<data format="binary">h[BinaryIP]</data> <!-- @IP dest -->
  	</sendMessageETHERNET>
	
	<finally>
		<removeProbeETHERNET name="capture" />
	</finally>
</scenario>